LICENSE.md
MANIFEST.in
README.rst
pyproject.toml
requirements.core.txt
setup.py
core_dashboard_common_app/__init__.py
core_dashboard_common_app/constants.py
core_dashboard_common_app/settings.py
core_dashboard_common_app.egg-info/PKG-INFO
core_dashboard_common_app.egg-info/SOURCES.txt
core_dashboard_common_app.egg-info/dependency_links.txt
core_dashboard_common_app.egg-info/requires.txt
core_dashboard_common_app.egg-info/top_level.txt
core_dashboard_common_app/static/core_dashboard_common_app/admin/js/action_dashboard.js
core_dashboard_common_app/static/core_dashboard_common_app/admin/js/count_checked.js
core_dashboard_common_app/static/core_dashboard_common_app/admin/js/get_selected_document_admin.js
core_dashboard_common_app/static/core_dashboard_common_app/admin/js/init_admin_menu.js
core_dashboard_common_app/static/core_dashboard_common_app/admin/js/my_dashboard_tabs.raw.js
core_dashboard_common_app/static/core_dashboard_common_app/admin/js/reset_checkbox.js
core_dashboard_common_app/static/core_dashboard_common_app/admin/js/select_all.js
core_dashboard_common_app/static/core_dashboard_common_app/admin/js/list/view_record.raw.js
core_dashboard_common_app/static/core_dashboard_common_app/common/css/content_query.css
core_dashboard_common_app/static/core_dashboard_common_app/common/css/list.css
core_dashboard_common_app/static/core_dashboard_common_app/common/css/password_form.css
core_dashboard_common_app/static/core_dashboard_common_app/common/js/init_pagination.js
core_dashboard_common_app/static/core_dashboard_common_app/common/js/persistent_query_config.js
core_dashboard_common_app/static/core_dashboard_common_app/common/js/list/delete_data_draft.js
core_dashboard_common_app/static/core_dashboard_common_app/common/js/list/delete_data_draft.raw.js
core_dashboard_common_app/static/core_dashboard_common_app/common/js/list/open_document.js
core_dashboard_common_app/static/core_dashboard_common_app/common/js/list/open_form.raw.js
core_dashboard_common_app/static/core_dashboard_common_app/common/js/list/open_record.raw.js
core_dashboard_common_app/static/core_dashboard_common_app/common/js/list/open_template.raw.js
core_dashboard_common_app/static/core_dashboard_common_app/common/js/list/view_record.js
